stonewave_sql_udtfs_example/__init__.py
stonewave_sql_udtfs_example/info.toml
stonewave_sql_udtfs_example/version.py
stonewave_sql_udtfs_example-0.1.0.1.dist-info/WHEEL
stonewave_sql_udtfs_example-0.1.0.1.dist-info/METADATA
stonewave_sql_udtfs_example-0.1.0.1.dist-info/RECORD
