Metadata-Version: 2.1
Name: stonewave-sql-udtfs-example
Version: 0.1.0.1
Summary: example python user defined table function for stonewave service
Author: Jiangtao Peng
Author-email: pengjiangtao@yanhuangdata.com
Requires-Python: >=3.9,<4.0
Classifier: Programming Language :: Python :: 3
Classifier: Programming Language :: Python :: 3.9
